{
 "version": "2.0.0",
 "scrollSpeed": {
  "easy": 1.8,
  "hard": 2.5,
  "normal": 2.2
 },
 "events": [
  {
   "t": 0,
   "e": "FocusCamera",
   "v": {
	"char": 2,
	"y": 100
}
  },
  {
   "t": 3840,
   "e": "FocusCamera",
   "v": {
	"char": 1,
	"y": 0
}
  },
  {
   "t": 5760,
   "e": "FocusCamera",
   "v": {
	"char": 0,
	"y": 0
}
  },
  {
   "t": 7680,
   "e": "FocusCamera",
   "v": 1
  },
  {
   "t": 15360,
   "e": "FocusCamera",
   "v": 0
  },
  {
   "t": 21120,
   "e": "FocusCamera",
   "v": {
	"char": 0
}
  },
  {
   "t": 23040,
   "e": "FocusCamera",
   "v": 1
  },
  {
   "t": 28800,
   "e": "FocusCamera",
   "v": {
	"char": 2,
	"y": 100
}
  },
  {
   "t": 30720,
   "e": "FocusCamera",
   "v": 0
  },
  {
   "t": 38400,
   "e": "FocusCamera",
   "v": 1
  },
  {
   "t": 41760,
   "e": "FocusCamera",
   "v": {
	"char": 2,
	"y": 100
}
  },
  {
   "t": 46080,
   "e": "FocusCamera",
   "v": 0
  },
  {
   "t": 53760,
   "e": "FocusCamera",
   "v": 1
  },
  {
   "t": 61440,
   "e": "FocusCamera",
   "v": 0
  },
  {
   "t": 69120,
   "e": "FocusCamera",
   "v": 1
  },
  {
   "t": 76800,
   "e": "FocusCamera",
   "v": 0
  },
  {
   "t": 84480,
   "e": "FocusCamera",
   "v": {
	"char": 2,
	"y": 100
}
  },
  {
   "t": 88320,
   "e": "FocusCamera",
   "v": {
	"char": 1,
	"y": 0
}
  },
  {
   "t": 92160,
   "e": "FocusCamera",
   "v": {
	"char": 2,
	"y": 100
}
  },
  {
   "t": 96000,
   "e": "FocusCamera",
   "v": 0
  },
  {
   "t": 99840,
   "e": "FocusCamera",
   "v": {
	"char": 2,
	"y": 100
}
  }
 ],
 "notes": {
  "easy": [],
  "hard": [
   {
    "t": 7680,
    "d": 4,
    "l": 0,
    "p": []
   },
   {
    "t": 8160,
    "d": 7,
    "l": 0,
    "p": []
   },
   {
    "t": 8400,
    "d": 6,
    "l": 0,
    "p": []
   },
   {
    "t": 8640,
    "d": 4,
    "l": 0,
    "p": []
   },
   {
    "t": 8760,
    "d": 5,
    "l": 0,
    "p": []
   },
   {
    "t": 9000,
    "d": 7,
    "l": 0,
    "p": []
   },
   {
    "t": 9360,
    "d": 6,
    "l": 0,
    "p": []
   },
   {
    "t": 9600,
    "d": 4,
    "l": 0,
    "p": []
   },
   {
    "t": 10080,
    "d": 5,
    "l": 0,
    "p": []
   },
   {
    "t": 10320,
    "d": 7,
    "l": 0,
    "p": []
   },
   {
    "t": 10560,
    "d": 6,
    "l": 150,
    "p": []
   },
   {
    "t": 10800,
    "d": 5,
    "l": 0,
    "p": []
   },
   {
    "t": 10920,
    "d": 7,
    "l": 150,
    "p": []
   },
   {
    "t": 11280,
    "d": 4,
    "l": 0,
    "p": []
   },
   {
    "t": 11400,
    "d": 7,
    "l": 0,
    "p": []
   },
   {
    "t": 11520,
    "d": 4,
    "l": 150,
    "p": []
   },
   {
    "t": 12000,
    "d": 5,
    "l": 0,
    "p": []
   },
   {
    "t": 12240,
    "d": 6,
    "l": 0,
    "p": []
   },
   {
    "t": 12480,
    "d": 5,
    "l": 0,
    "p": []
   },
   {
    "t": 12600,
    "d": 7,
    "l": 0,
    "p": []
   },
   {
    "t": 12840,
    "d": 5,
    "l": 0,
    "p": []
   },
   {
    "t": 13200,
    "d": 4,
    "l": 0,
    "p": []
   },
   {
    "t": 13440,
    "d": 5,
    "l": 0,
    "p": []
   },
   {
    "t": 13560,
    "d": 6,
    "l": 0,
    "p": []
   },
   {
    "t": 13680,
    "d": 4,
    "l": 0,
    "p": []
   },
   {
    "t": 13800,
    "d": 5,
    "l": 0,
    "p": []
   },
   {
    "t": 13920,
    "d": 7,
    "l": 150,
    "p": []
   },
   {
    "t": 14160,
    "d": 5,
    "l": 0,
    "p": []
   },
   {
    "t": 14280,
    "d": 6,
    "l": 0,
    "p": []
   },
   {
    "t": 14400,
    "d": 4,
    "l": 0,
    "p": []
   },
   {
    "t": 14640,
    "d": 5,
    "l": 0,
    "p": []
   },
   {
    "t": 14880,
    "d": 7,
    "l": 0,
    "p": []
   },
   {
    "t": 15000,
    "d": 5,
    "l": 0,
    "p": []
   },
   {
    "t": 15120,
    "d": 6,
    "l": 0,
    "p": []
   },
   {
    "t": 15360,
    "d": 0,
    "l": 0,
    "p": []
   },
   {
    "t": 15600,
    "d": 4,
    "l": 0,
    "p": []
   },
   {
    "t": 15840,
    "d": 3,
    "l": 0,
    "p": []
   },
   {
    "t": 16080,
    "d": 4,
    "l": 0,
    "p": []
   },
   {
    "t": 16080,
    "d": 2,
    "l": 0,
    "p": []
   },
   {
    "t": 16320,
    "d": 0,
    "l": 0,
    "p": []
   },
   {
    "t": 16440,
    "d": 1,
    "l": 0,
    "p": []
   },
   {
    "t": 16560,
    "d": 4,
    "l": 0,
    "p": []
   },
   {
    "t": 16680,
    "d": 3,
    "l": 0,
    "p": []
   },
   {
    "t": 17040,
    "d": 4,
    "l": 0,
    "p": []
   },
   {
    "t": 17040,
    "d": 2,
    "l": 0,
    "p": []
   },
   {
    "t": 17280,
    "d": 0,
    "l": 0,
    "p": []
   },
   {
    "t": 17520,
    "d": 4,
    "l": 0,
    "p": []
   },
   {
    "t": 17760,
    "d": 1,
    "l": 0,
    "p": []
   },
   {
    "t": 18000,
    "d": 4,
    "l": 0,
    "p": []
   },
   {
    "t": 18000,
    "d": 3,
    "l": 0,
    "p": []
   },
   {
    "t": 18240,
    "d": 2,
    "l": 0,
    "p": []
   },
   {
    "t": 18360,
    "d": 0,
    "l": 0,
    "p": []
   },
   {
    "t": 18600,
    "d": 3,
    "l": 150,
    "p": []
   },
   {
    "t": 18960,
    "d": 0,
    "l": 0,
    "p": []
   },
   {
    "t": 19080,
    "d": 3,
    "l": 0,
    "p": []
   },
   {
    "t": 19200,
    "d": 0,
    "l": 150,
    "p": []
   },
   {
    "t": 19680,
    "d": 1,
    "l": 0,
    "p": []
   },
   {
    "t": 19920,
    "d": 2,
    "l": 0,
    "p": []
   },
   {
    "t": 20160,
    "d": 1,
    "l": 0,
    "p": []
   },
   {
    "t": 20280,
    "d": 3,
    "l": 0,
    "p": []
   },
   {
    "t": 20520,
    "d": 1,
    "l": 0,
    "p": []
   },
   {
    "t": 20880,
    "d": 0,
    "l": 0,
    "p": []
   },
   {
    "t": 21120,
    "d": 1,
    "l": 0,
    "p": []
   },
   {
    "t": 21120,
    "d": 4,
    "l": 270,
    "p": []
   },
   {
    "t": 21240,
    "d": 2,
    "l": 0,
    "p": []
   },
   {
    "t": 21360,
    "d": 0,
    "l": 0,
    "p": []
   },
   {
    "t": 21480,
    "d": 1,
    "l": 0,
    "p": []
   },
   {
    "t": 21600,
    "d": 3,
    "l": 150,
    "p": []
   },
   {
    "t": 21630,
    "d": 5,
    "l": 240,
    "p": []
   },
   {
    "t": 21840,
    "d": 1,
    "l": 0,
    "p": []
   },
   {
    "t": 21960,
    "d": 2,
    "l": 0,
    "p": []
   },
   {
    "t": 22080,
    "d": 0,
    "l": 0,
    "p": []
   },
   {
    "t": 22080,
    "d": 7,
    "l": 270,
    "p": []
   },
   {
    "t": 22320,
    "d": 1,
    "l": 0,
    "p": []
   },
   {
    "t": 22560,
    "d": 3,
    "l": 0,
    "p": []
   },
   {
    "t": 22560,
    "d": 6,
    "l": 270,
    "p": []
   },
   {
    "t": 22680,
    "d": 1,
    "l": 0,
    "p": []
   },
   {
    "t": 22800,
    "d": 2,
    "l": 0,
    "p": []
   },
   {
    "t": 23040,
    "d": 4,
    "l": 0,
    "p": []
   },
   {
    "t": 23280,
    "d": 5,
    "l": 0,
    "p": []
   },
   {
    "t": 23400,
    "d": 7,
    "l": 0,
    "p": []
   },
   {
    "t": 23520,
    "d": 6,
    "l": 0,
    "p": []
   },
   {
    "t": 23760,
    "d": 4,
    "l": 0,
    "p": []
   },
   {
    "t": 23880,
    "d": 5,
    "l": 0,
    "p": []
   },
   {
    "t": 24000,
    "d": 7,
    "l": 0,
    "p": []
   },
   {
    "t": 24120,
    "d": 6,
    "l": 0,
    "p": []
   },
   {
    "t": 24240,
    "d": 4,
    "l": 0,
    "p": []
   },
   {
    "t": 24360,
    "d": 7,
    "l": 0,
    "p": []
   },
   {
    "t": 24720,
    "d": 4,
    "l": 0,
    "p": []
   },
   {
    "t": 24840,
    "d": 6,
    "l": 0,
    "p": []
   },
   {
    "t": 25200,
    "d": 4,
    "l": 0,
    "p": []
   },
   {
    "t": 25320,
    "d": 5,
    "l": 0,
    "p": []
   },
   {
    "t": 25440,
    "d": 6,
    "l": 0,
    "p": []
   },
   {
    "t": 25680,
    "d": 7,
    "l": 0,
    "p": []
   },
   {
    "t": 25800,
    "d": 4,
    "l": 0,
    "p": []
   },
   {
    "t": 25920,
    "d": 6,
    "l": 150,
    "p": []
   },
   {
    "t": 26040,
    "d": 5,
    "l": 270,
    "p": []
   },
   {
    "t": 26310,
    "d": 6,
    "l": 150,
    "p": []
   },
   {
    "t": 26640,
    "d": 4,
    "l": 0,
    "p": []
   },
   {
    "t": 26760,
    "d": 7,
    "l": 0,
    "p": []
   },
   {
    "t": 27120,
    "d": 4,
    "l": 0,
    "p": []
   },
   {
    "t": 27240,
    "d": 5,
    "l": 0,
    "p": []
   },
   {
    "t": 27360,
    "d": 6,
    "l": 0,
    "p": []
   },
   {
    "t": 27720,
    "d": 7,
    "l": 0,
    "p": []
   },
   {
    "t": 27840,
    "d": 6,
    "l": 0,
    "p": []
   },
   {
    "t": 28200,
    "d": 4,
    "l": 0,
    "p": []
   },
   {
    "t": 28560,
    "d": 6,
    "l": 0,
    "p": []
   },
   {
    "t": 28680,
    "d": 7,
    "l": 0,
    "p": []
   },
   {
    "t": 28800,
    "d": 4,
    "l": 0,
    "p": []
   },
   {
    "t": 28800,
    "d": 2,
    "l": 270,
    "p": []
   },
   {
    "t": 28920,
    "d": 5,
    "l": 0,
    "p": []
   },
   {
    "t": 29040,
    "d": 6,
    "l": 0,
    "p": []
   },
   {
    "t": 29280,
    "d": 5,
    "l": 0,
    "p": []
   },
   {
    "t": 29280,
    "d": 0,
    "l": 270,
    "p": []
   },
   {
    "t": 29520,
    "d": 7,
    "l": 0,
    "p": []
   },
   {
    "t": 29760,
    "d": 4,
    "l": 0,
    "p": []
   },
   {
    "t": 29760,
    "d": 3,
    "l": 270,
    "p": []
   },
   {
    "t": 29880,
    "d": 5,
    "l": 0,
    "p": []
   },
   {
    "t": 30000,
    "d": 4,
    "l": 0,
    "p": []
   },
   {
    "t": 30120,
    "d": 5,
    "l": 0,
    "p": []
   },
   {
    "t": 30240,
    "d": 6,
    "l": 0,
    "p": []
   },
   {
    "t": 30240,
    "d": 1,
    "l": 270,
    "p": []
   },
   {
    "t": 30360,
    "d": 7,
    "l": 0,
    "p": []
   },
   {
    "t": 30480,
    "d": 4,
    "l": 0,
    "p": []
   },
   {
    "t": 30600,
    "d": 7,
    "l": 0,
    "p": []
   },
   {
    "t": 30720,
    "d": 2,
    "l": 0,
    "p": []
   },
   {
    "t": 30960,
    "d": 1,
    "l": 0,
    "p": []
   },
   {
    "t": 31080,
    "d": 3,
    "l": 0,
    "p": []
   },
   {
    "t": 31200,
    "d": 2,
    "l": 0,
    "p": []
   },
   {
    "t": 31440,
    "d": 0,
    "l": 0,
    "p": []
   },
   {
    "t": 31560,
    "d": 1,
    "l": 0,
    "p": []
   },
   {
    "t": 31680,
    "d": 3,
    "l": 0,
    "p": []
   },
   {
    "t": 31800,
    "d": 2,
    "l": 0,
    "p": []
   },
   {
    "t": 31920,
    "d": 0,
    "l": 0,
    "p": []
   },
   {
    "t": 32040,
    "d": 3,
    "l": 0,
    "p": []
   },
   {
    "t": 32400,
    "d": 0,
    "l": 0,
    "p": []
   },
   {
    "t": 32520,
    "d": 2,
    "l": 0,
    "p": []
   },
   {
    "t": 32880,
    "d": 0,
    "l": 0,
    "p": []
   },
   {
    "t": 33000,
    "d": 1,
    "l": 0,
    "p": []
   },
   {
    "t": 33120,
    "d": 2,
    "l": 0,
    "p": []
   },
   {
    "t": 33360,
    "d": 3,
    "l": 0,
    "p": []
   },
   {
    "t": 33480,
    "d": 0,
    "l": 0,
    "p": []
   },
   {
    "t": 33600,
    "d": 2,
    "l": 0,
    "p": []
   },
   {
    "t": 33720,
    "d": 1,
    "l": 150,
    "p": []
   },
   {
    "t": 33990,
    "d": 2,
    "l": 150,
    "p": []
   },
   {
    "t": 34320,
    "d": 0,
    "l": 0,
    "p": []
   },
   {
    "t": 34440,
    "d": 3,
    "l": 0,
    "p": []
   },
   {
    "t": 34800,
    "d": 0,
    "l": 0,
    "p": []
   },
   {
    "t": 34920,
    "d": 1,
    "l": 0,
    "p": []
   },
   {
    "t": 35040,
    "d": 2,
    "l": 0,
    "p": []
   },
   {
    "t": 35400,
    "d": 3,
    "l": 0,
    "p": []
   },
   {
    "t": 35520,
    "d": 2,
    "l": 0,
    "p": []
   },
   {
    "t": 35880,
    "d": 0,
    "l": 0,
    "p": []
   },
   {
    "t": 36240,
    "d": 2,
    "l": 0,
    "p": []
   },
   {
    "t": 36360,
    "d": 3,
    "l": 0,
    "p": []
   },
   {
    "t": 36480,
    "d": 0,
    "l": 0,
    "p": []
   },
   {
    "t": 36600,
    "d": 1,
    "l": 0,
    "p": []
   },
   {
    "t": 36720,
    "d": 2,
    "l": 0,
    "p": []
   },
   {
    "t": 36960,
    "d": 1,
    "l": 0,
    "p": []
   },
   {
    "t": 37200,
    "d": 3,
    "l": 0,
    "p": []
   },
   {
    "t": 37440,
    "d": 0,
    "l": 0,
    "p": []
   },
   {
    "t": 37560,
    "d": 1,
    "l": 0,
    "p": []
   },
   {
    "t": 37680,
    "d": 0,
    "l": 0,
    "p": []
   },
   {
    "t": 37800,
    "d": 1,
    "l": 0,
    "p": []
   },
   {
    "t": 37920,
    "d": 2,
    "l": 0,
    "p": []
   },
   {
    "t": 38040,
    "d": 3,
    "l": 0,
    "p": []
   },
   {
    "t": 38160,
    "d": 0,
    "l": 0,
    "p": []
   },
   {
    "t": 38280,
    "d": 3,
    "l": 0,
    "p": []
   },
   {
    "t": 38400,
    "d": 4,
    "l": 0,
    "p": []
   },
   {
    "t": 38520,
    "d": 6,
    "l": 0,
    "p": []
   },
   {
    "t": 38640,
    "d": 5,
    "l": 0,
    "p": []
   },
   {
    "t": 38760,
    "d": 6,
    "l": 0,
    "p": []
   },
   {
    "t": 38880,
    "d": 7,
    "l": 270,
    "p": []
   },
   {
    "t": 39360,
    "d": 5,
    "l": 270,
    "p": []
   },
   {
    "t": 39840,
    "d": 4,
    "l": 270,
    "p": []
   },
   {
    "t": 40320,
    "d": 6,
    "l": 0,
    "p": []
   },
   {
    "t": 40680,
    "d": 7,
    "l": 0,
    "p": []
   },
   {
    "t": 40800,
    "d": 4,
    "l": 0,
    "p": []
   },
   {
    "t": 40920,
    "d": 5,
    "l": 0,
    "p": []
   },
   {
    "t": 41040,
    "d": 6,
    "l": 0,
    "p": []
   },
   {
    "t": 41160,
    "d": 4,
    "l": 0,
    "p": []
   },
   {
    "t": 41280,
    "d": 5,
    "l": 150,
    "p": []
   },
   {
    "t": 41640,
    "d": 7,
    "l": 0,
    "p": []
   },
   {
    "t": 41760,
    "d": 6,
    "l": 150,
    "p": []
   },
   {
    "t": 41760,
    "d": 1,
    "l": 270,
    "p": []
   },
   {
    "t": 42120,
    "d": 4,
    "l": 0,
    "p": []
   },
   {
    "t": 42240,
    "d": 7,
    "l": 270,
    "p": []
   },
   {
    "t": 42240,
    "d": 3,
    "l": 750,
    "p": []
   },
   {
    "t": 42720,
    "d": 6,
    "l": 270,
    "p": []
   },
   {
    "t": 43200,
    "d": 4,
    "l": 270,
    "p": []
   },
   {
    "t": 43680,
    "d": 7,
    "l": 270,
    "p": []
   },
   {
    "t": 44160,
    "d": 4,
    "l": 0,
    "p": []
   },
   {
    "t": 44160,
    "d": 0,
    "l": 630,
    "p": []
   },
   {
    "t": 44280,
    "d": 5,
    "l": 0,
    "p": []
   },
   {
    "t": 44400,
    "d": 6,
    "l": 0,
    "p": []
   },
   {
    "t": 44520,
    "d": 4,
    "l": 0,
    "p": []
   },
   {
    "t": 44640,
    "d": 7,
    "l": 0,
    "p": []
   },
   {
    "t": 44760,
    "d": 5,
    "l": 0,
    "p": []
   },
   {
    "t": 44880,
    "d": 6,
    "l": 0,
    "p": []
   },
   {
    "t": 45000,
    "d": 4,
    "l": 0,
    "p": []
   },
   {
    "t": 45120,
    "d": 6,
    "l": 150,
    "p": []
   },
   {
    "t": 45120,
    "d": 1,
    "l": 630,
    "p": []
   },
   {
    "t": 45480,
    "d": 5,
    "l": 0,
    "p": []
   },
   {
    "t": 45600,
    "d": 7,
    "l": 150,
    "p": []
   },
   {
    "t": 45960,
    "d": 4,
    "l": 0,
    "p": []
   },
   {
    "t": 46080,
    "d": 0,
    "l": 0,
    "p": []
   },
   {
    "t": 46200,
    "d": 5,
    "l": 270,
    "p": []
   },
   {
    "t": 46200,
    "d": 2,
    "l": 0,
    "p": []
   },
   {
    "t": 46320,
    "d": 1,
    "l": 0,
    "p": []
   },
   {
    "t": 46440,
    "d": 2,
    "l": 0,
    "p": []
   },
   {
    "t": 46560,
    "d": 3,
    "l": 270,
    "p": []
   },
   {
    "t": 46560,
    "d": 4,
    "l": 270,
    "p": []
   },
   {
    "t": 47040,
    "d": 1,
    "l": 270,
    "p": []
   },
   {
    "t": 47040,
    "d": 7,
    "l": 270,
    "p": []
   },
   {
    "t": 47520,
    "d": 0,
    "l": 270,
    "p": []
   },
   {
    "t": 47520,
    "d": 6,
    "l": 270,
    "p": []
   },
   {
    "t": 48000,
    "d": 2,
    "l": 0,
    "p": []
   },
   {
    "t": 48000,
    "d": 7,
    "l": 0,
    "p": []
   },
   {
    "t": 48360,
    "d": 3,
    "l": 0,
    "p": []
   },
   {
    "t": 48480,
    "d": 0,
    "l": 0,
    "p": []
   },
   {
    "t": 48600,
    "d": 3,
    "l": 0,
    "p": []
   },
   {
    "t": 48720,
    "d": 1,
    "l": 0,
    "p": []
   },
   {
    "t": 48840,
    "d": 0,
    "l": 0,
    "p": []
   },
   {
    "t": 48960,
    "d": 2,
    "l": 150,
    "p": []
   },
   {
    "t": 48960,
    "d": 6,
    "l": 150,
    "p": []
   },
   {
    "t": 49320,
    "d": 3,
    "l": 0,
    "p": []
   },
   {
    "t": 49320,
    "d": 4,
    "l": 0,
    "p": []
   },
   {
    "t": 49440,
    "d": 1,
    "l": 150,
    "p": []
   },
   {
    "t": 49440,
    "d": 5,
    "l": 150,
    "p": []
   },
   {
    "t": 49800,
    "d": 0,
    "l": 0,
    "p": []
   },
   {
    "t": 49800,
    "d": 7,
    "l": 0,
    "p": []
   },
   {
    "t": 49920,
    "d": 3,
    "l": 270,
    "p": []
   },
   {
    "t": 49920,
    "d": 6,
    "l": 270,
    "p": []
   },
   {
    "t": 50400,
    "d": 2,
    "l": 270,
    "p": []
   },
   {
    "t": 50400,
    "d": 4,
    "l": 1230,
    "p": []
   },
   {
    "t": 50880,
    "d": 0,
    "l": 270,
    "p": []
   },
   {
    "t": 51360,
    "d": 2,
    "l": 270,
    "p": []
   },
   {
    "t": 51840,
    "d": 0,
    "l": 0,
    "p": []
   },
   {
    "t": 51960,
    "d": 1,
    "l": 0,
    "p": []
   },
   {
    "t": 52080,
    "d": 2,
    "l": 0,
    "p": []
   },
   {
    "t": 52200,
    "d": 0,
    "l": 0,
    "p": []
   },
   {
    "t": 52320,
    "d": 3,
    "l": 0,
    "p": []
   },
   {
    "t": 52440,
    "d": 1,
    "l": 0,
    "p": []
   },
   {
    "t": 52560,
    "d": 2,
    "l": 0,
    "p": []
   },
   {
    "t": 52680,
    "d": 0,
    "l": 0,
    "p": []
   },
   {
    "t": 52800,
    "d": 2,
    "l": 150,
    "p": []
   },
   {
    "t": 53160,
    "d": 1,
    "l": 0,
    "p": []
   },
   {
    "t": 53280,
    "d": 3,
    "l": 150,
    "p": []
   },
   {
    "t": 53640,
    "d": 0,
    "l": 0,
    "p": []
   },
   {
    "t": 53760,
    "d": 1,
    "l": 510,
    "p": []
   },
   {
    "t": 53760,
    "d": 4,
    "l": 510,
    "p": []
   },
   {
    "t": 54480,
    "d": 7,
    "l": 0,
    "p": []
   },
   {
    "t": 54720,
    "d": 6,
    "l": 0,
    "p": []
   },
   {
    "t": 54840,
    "d": 4,
    "l": 0,
    "p": []
   },
   {
    "t": 55080,
    "d": 5,
    "l": 0,
    "p": []
   },
   {
    "t": 55200,
    "d": 7,
    "l": 0,
    "p": []
   },
   {
    "t": 55560,
    "d": 4,
    "l": 0,
    "p": []
   },
   {
    "t": 55680,
    "d": 6,
    "l": 270,
    "p": []
   },
   {
    "t": 56160,
    "d": 5,
    "l": 0,
    "p": []
   },
   {
    "t": 56400,
    "d": 7,
    "l": 0,
    "p": []
   },
   {
    "t": 56640,
    "d": 4,
    "l": 0,
    "p": []
   },
   {
    "t": 56760,
    "d": 6,
    "l": 0,
    "p": []
   },
   {
    "t": 57000,
    "d": 7,
    "l": 0,
    "p": []
   },
   {
    "t": 57120,
    "d": 5,
    "l": 0,
    "p": []
   },
   {
    "t": 57480,
    "d": 4,
    "l": 0,
    "p": []
   },
   {
    "t": 57600,
    "d": 5,
    "l": 270,
    "p": []
   },
   {
    "t": 58080,
    "d": 7,
    "l": 0,
    "p": []
   },
   {
    "t": 58320,
    "d": 4,
    "l": 0,
    "p": []
   },
   {
    "t": 58560,
    "d": 5,
    "l": 0,
    "p": []
   },
   {
    "t": 58680,
    "d": 6,
    "l": 0,
    "p": []
   },
   {
    "t": 58920,
    "d": 4,
    "l": 0,
    "p": []
   },
   {
    "t": 59040,
    "d": 7,
    "l": 0,
    "p": []
   },
   {
    "t": 59400,
    "d": 6,
    "l": 0,
    "p": []
   },
   {
    "t": 59520,
    "d": 4,
    "l": 0,
    "p": []
   },
   {
    "t": 59760,
    "d": 5,
    "l": 0,
    "p": []
   },
   {
    "t": 59880,
    "d": 6,
    "l": 0,
    "p": []
   },
   {
    "t": 60000,
    "d": 7,
    "l": 0,
    "p": []
   },
   {
    "t": 60120,
    "d": 4,
    "l": 0,
    "p": []
   },
   {
    "t": 60240,
    "d": 6,
    "l": 0,
    "p": []
   },
   {
    "t": 60360,
    "d": 5,
    "l": 0,
    "p": []
   },
   {
    "t": 60480,
    "d": 7,
    "l": 0,
    "p": []
   },
   {
    "t": 60600,
    "d": 5,
    "l": 0,
    "p": []
   },
   {
    "t": 60720,
    "d": 4,
    "l": 0,
    "p": []
   },
   {
    "t": 60960,
    "d": 6,
    "l": 0,
    "p": []
   },
   {
    "t": 61200,
    "d": 7,
    "l": 0,
    "p": []
   },
   {
    "t": 61440,
    "d": 6,
    "l": 510,
    "p": []
   },
   {
    "t": 61440,
    "d": 0,
    "l": 510,
    "p": []
   },
   {
    "t": 62160,
    "d": 3,
    "l": 0,
    "p": []
   },
   {
    "t": 62400,
    "d": 2,
    "l": 0,
    "p": []
   },
   {
    "t": 62520,
    "d": 0,
    "l": 0,
    "p": []
   },
   {
    "t": 62760,
    "d": 1,
    "l": 0,
    "p": []
   },
   {
    "t": 62880,
    "d": 3,
    "l": 0,
    "p": []
   },
   {
    "t": 63240,
    "d": 0,
    "l": 0,
    "p": []
   },
   {
    "t": 63360,
    "d": 2,
    "l": 270,
    "p": []
   },
   {
    "t": 63840,
    "d": 1,
    "l": 0,
    "p": []
   },
   {
    "t": 64080,
    "d": 3,
    "l": 0,
    "p": []
   },
   {
    "t": 64320,
    "d": 0,
    "l": 0,
    "p": []
   },
   {
    "t": 64440,
    "d": 2,
    "l": 0,
    "p": []
   },
   {
    "t": 64680,
    "d": 3,
    "l": 0,
    "p": []
   },
   {
    "t": 64800,
    "d": 1,
    "l": 0,
    "p": []
   },
   {
    "t": 65160,
    "d": 0,
    "l": 0,
    "p": []
   },
   {
    "t": 65280,
    "d": 1,
    "l": 270,
    "p": []
   },
   {
    "t": 65760,
    "d": 3,
    "l": 0,
    "p": []
   },
   {
    "t": 66000,
    "d": 0,
    "l": 0,
    "p": []
   },
   {
    "t": 66240,
    "d": 1,
    "l": 0,
    "p": []
   },
   {
    "t": 66360,
    "d": 2,
    "l": 0,
    "p": []
   },
   {
    "t": 66600,
    "d": 0,
    "l": 0,
    "p": []
   },
   {
    "t": 66720,
    "d": 3,
    "l": 0,
    "p": []
   },
   {
    "t": 67080,
    "d": 2,
    "l": 0,
    "p": []
   },
   {
    "t": 67200,
    "d": 0,
    "l": 0,
    "p": []
   },
   {
    "t": 67440,
    "d": 1,
    "l": 0,
    "p": []
   },
   {
    "t": 67560,
    "d": 2,
    "l": 0,
    "p": []
   },
   {
    "t": 67680,
    "d": 3,
    "l": 0,
    "p": []
   },
   {
    "t": 67800,
    "d": 0,
    "l": 0,
    "p": []
   },
   {
    "t": 67920,
    "d": 2,
    "l": 0,
    "p": []
   },
   {
    "t": 68040,
    "d": 1,
    "l": 0,
    "p": []
   },
   {
    "t": 68160,
    "d": 3,
    "l": 0,
    "p": []
   },
   {
    "t": 68280,
    "d": 1,
    "l": 0,
    "p": []
   },
   {
    "t": 68400,
    "d": 0,
    "l": 0,
    "p": []
   },
   {
    "t": 68640,
    "d": 2,
    "l": 0,
    "p": []
   },
   {
    "t": 68880,
    "d": 3,
    "l": 0,
    "p": []
   },
   {
    "t": 69120,
    "d": 2,
    "l": 510,
    "p": []
   },
   {
    "t": 69120,
    "d": 4,
    "l": 0,
    "p": []
   },
   {
    "t": 69240,
    "d": 6,
    "l": 0,
    "p": []
   },
   {
    "t": 69360,
    "d": 5,
    "l": 0,
    "p": []
   },
   {
    "t": 69480,
    "d": 6,
    "l": 0,
    "p": []
   },
   {
    "t": 69600,
    "d": 7,
    "l": 270,
    "p": []
   },
   {
    "t": 70080,
    "d": 5,
    "l": 270,
    "p": []
   },
   {
    "t": 70560,
    "d": 4,
    "l": 270,
    "p": []
   },
   {
    "t": 71040,
    "d": 6,
    "l": 0,
    "p": []
   },
   {
    "t": 71400,
    "d": 7,
    "l": 0,
    "p": []
   },
   {
    "t": 71520,
    "d": 4,
    "l": 0,
    "p": []
   },
   {
    "t": 71640,
    "d": 5,
    "l": 0,
    "p": []
   },
   {
    "t": 71760,
    "d": 6,
    "l": 0,
    "p": []
   },
   {
    "t": 71880,
    "d": 4,
    "l": 0,
    "p": []
   },
   {
    "t": 72000,
    "d": 5,
    "l": 150,
    "p": []
   },
   {
    "t": 72360,
    "d": 7,
    "l": 0,
    "p": []
   },
   {
    "t": 72480,
    "d": 6,
    "l": 150,
    "p": []
   },
   {
    "t": 72840,
    "d": 4,
    "l": 0,
    "p": []
   },
   {
    "t": 72960,
    "d": 7,
    "l": 270,
    "p": []
   },
   {
    "t": 73440,
    "d": 6,
    "l": 270,
    "p": []
   },
   {
    "t": 73920,
    "d": 4,
    "l": 270,
    "p": []
   },
   {
    "t": 74400,
    "d": 7,
    "l": 270,
    "p": []
   },
   {
    "t": 74880,
    "d": 4,
    "l": 0,
    "p": []
   },
   {
    "t": 75000,
    "d": 5,
    "l": 0,
    "p": []
   },
   {
    "t": 75120,
    "d": 6,
    "l": 0,
    "p": []
   },
   {
    "t": 75240,
    "d": 4,
    "l": 0,
    "p": []
   },
   {
    "t": 75360,
    "d": 7,
    "l": 0,
    "p": []
   },
   {
    "t": 75480,
    "d": 5,
    "l": 0,
    "p": []
   },
   {
    "t": 75600,
    "d": 6,
    "l": 0,
    "p": []
   },
   {
    "t": 75720,
    "d": 4,
    "l": 0,
    "p": []
   },
   {
    "t": 75840,
    "d": 6,
    "l": 150,
    "p": []
   },
   {
    "t": 76200,
    "d": 5,
    "l": 0,
    "p": []
   },
   {
    "t": 76320,
    "d": 7,
    "l": 150,
    "p": []
   },
   {
    "t": 76680,
    "d": 4,
    "l": 0,
    "p": []
   },
   {
    "t": 76800,
    "d": 0,
    "l": 0,
    "p": []
   },
   {
    "t": 76920,
    "d": 5,
    "l": 270,
    "p": []
   },
   {
    "t": 76920,
    "d": 2,
    "l": 0,
    "p": []
   },
   {
    "t": 77040,
    "d": 1,
    "l": 0,
    "p": []
   },
   {
    "t": 77160,
    "d": 2,
    "l": 0,
    "p": []
   },
   {
    "t": 77280,
    "d": 3,
    "l": 270,
    "p": []
   },
   {
    "t": 77280,
    "d": 4,
    "l": 270,
    "p": []
   },
   {
    "t": 77760,
    "d": 1,
    "l": 270,
    "p": []
   },
   {
    "t": 77760,
    "d": 7,
    "l": 270,
    "p": []
   },
   {
    "t": 78240,
    "d": 0,
    "l": 270,
    "p": []
   },
   {
    "t": 78240,
    "d": 6,
    "l": 270,
    "p": []
   },
   {
    "t": 78720,
    "d": 2,
    "l": 0,
    "p": []
   },
   {
    "t": 78720,
    "d": 7,
    "l": 0,
    "p": []
   },
   {
    "t": 79080,
    "d": 3,
    "l": 0,
    "p": []
   },
   {
    "t": 79200,
    "d": 0,
    "l": 0,
    "p": []
   },
   {
    "t": 79320,
    "d": 3,
    "l": 0,
    "p": []
   },
   {
    "t": 79440,
    "d": 1,
    "l": 0,
    "p": []
   },
   {
    "t": 79560,
    "d": 0,
    "l": 0,
    "p": []
   },
   {
    "t": 79680,
    "d": 2,
    "l": 150,
    "p": []
   },
   {
    "t": 79680,
    "d": 6,
    "l": 150,
    "p": []
   },
   {
    "t": 80040,
    "d": 3,
    "l": 0,
    "p": []
   },
   {
    "t": 80040,
    "d": 4,
    "l": 0,
    "p": []
   },
   {
    "t": 80160,
    "d": 1,
    "l": 150,
    "p": []
   },
   {
    "t": 80160,
    "d": 5,
    "l": 150,
    "p": []
   },
   {
    "t": 80520,
    "d": 0,
    "l": 0,
    "p": []
   },
   {
    "t": 80520,
    "d": 7,
    "l": 0,
    "p": []
   },
   {
    "t": 80640,
    "d": 3,
    "l": 270,
    "p": []
   },
   {
    "t": 80640,
    "d": 6,
    "l": 270,
    "p": []
   },
   {
    "t": 81120,
    "d": 2,
    "l": 270,
    "p": []
   },
   {
    "t": 81120,
    "d": 4,
    "l": 1230,
    "p": []
   },
   {
    "t": 81600,
    "d": 0,
    "l": 270,
    "p": []
   },
   {
    "t": 82080,
    "d": 2,
    "l": 270,
    "p": []
   },
   {
    "t": 82560,
    "d": 0,
    "l": 0,
    "p": []
   },
   {
    "t": 82680,
    "d": 1,
    "l": 0,
    "p": []
   },
   {
    "t": 82800,
    "d": 2,
    "l": 0,
    "p": []
   },
   {
    "t": 82920,
    "d": 0,
    "l": 0,
    "p": []
   },
   {
    "t": 83040,
    "d": 3,
    "l": 0,
    "p": []
   },
   {
    "t": 83160,
    "d": 1,
    "l": 0,
    "p": []
   },
   {
    "t": 83280,
    "d": 2,
    "l": 0,
    "p": []
   },
   {
    "t": 83400,
    "d": 0,
    "l": 0,
    "p": []
   },
   {
    "t": 83520,
    "d": 2,
    "l": 150,
    "p": []
   },
   {
    "t": 83880,
    "d": 1,
    "l": 0,
    "p": []
   },
   {
    "t": 84000,
    "d": 3,
    "l": 150,
    "p": []
   },
   {
    "t": 84360,
    "d": 0,
    "l": 0,
    "p": []
   },
   {
    "t": 84480,
    "d": 7,
    "l": 990,
    "p": []
   },
   {
    "t": 84480,
    "d": 1,
    "l": 990,
    "p": []
   },
   {
    "t": 85920,
    "d": 4,
    "l": 270,
    "p": []
   },
   {
    "t": 85920,
    "d": 3,
    "l": 270,
    "p": []
   },
   {
    "t": 86400,
    "d": 2,
    "l": 270,
    "p": []
   },
   {
    "t": 86400,
    "d": 7,
    "l": 510,
    "p": []
   },
   {
    "t": 86880,
    "d": 0,
    "l": 0,
    "p": []
   },
   {
    "t": 87120,
    "d": 3,
    "l": 270,
    "p": []
   },
   {
    "t": 87120,
    "d": 6,
    "l": 390,
    "p": []
   },
   {
    "t": 87600,
    "d": 2,
    "l": 0,
    "p": []
   },
   {
    "t": 87840,
    "d": 4,
    "l": 0,
    "p": []
   },
   {
    "t": 87840,
    "d": 5,
    "l": 0,
    "p": []
   },
   {
    "t": 87840,
    "d": 0,
    "l": 270,
    "p": []
   },
   {
    "t": 88320,
    "d": 6,
    "l": 0,
    "p": []
   },
   {
    "t": 88320,
    "d": 2,
    "l": 270,
    "p": []
   },
   {
    "t": 88440,
    "d": 4,
    "l": 0,
    "p": []
   },
   {
    "t": 88560,
    "d": 5,
    "l": 0,
    "p": []
   },
   {
    "t": 88680,
    "d": 7,
    "l": 0,
    "p": []
   },
   {
    "t": 88800,
    "d": 5,
    "l": 0,
    "p": []
   },
   {
    "t": 88800,
    "d": 0,
    "l": 270,
    "p": []
   },
   {
    "t": 88920,
    "d": 4,
    "l": 0,
    "p": []
   },
   {
    "t": 89040,
    "d": 6,
    "l": 0,
    "p": []
   },
   {
    "t": 89160,
    "d": 4,
    "l": 0,
    "p": []
   },
   {
    "t": 89280,
    "d": 7,
    "l": 0,
    "p": []
   },
   {
    "t": 89280,
    "d": 3,
    "l": 270,
    "p": []
   },
   {
    "t": 89400,
    "d": 5,
    "l": 0,
    "p": []
   },
   {
    "t": 89520,
    "d": 7,
    "l": 0,
    "p": []
   },
   {
    "t": 89640,
    "d": 4,
    "l": 0,
    "p": []
   },
   {
    "t": 89760,
    "d": 6,
    "l": 0,
    "p": []
   },
   {
    "t": 89760,
    "d": 2,
    "l": 270,
    "p": []
   },
   {
    "t": 89880,
    "d": 5,
    "l": 0,
    "p": []
   },
   {
    "t": 90000,
    "d": 7,
    "l": 0,
    "p": []
   },
   {
    "t": 90120,
    "d": 4,
    "l": 0,
    "p": []
   },
   {
    "t": 90240,
    "d": 5,
    "l": 0,
    "p": []
   },
   {
    "t": 90240,
    "d": 0,
    "l": 270,
    "p": []
   },
   {
    "t": 90360,
    "d": 6,
    "l": 0,
    "p": []
   },
   {
    "t": 90480,
    "d": 4,
    "l": 0,
    "p": []
   },
   {
    "t": 90600,
    "d": 7,
    "l": 0,
    "p": []
   },
   {
    "t": 90720,
    "d": 5,
    "l": 0,
    "p": []
   },
   {
    "t": 90720,
    "d": 3,
    "l": 270,
    "p": []
   },
   {
    "t": 90840,
    "d": 6,
    "l": 0,
    "p": []
   },
   {
    "t": 90960,
    "d": 4,
    "l": 0,
    "p": []
   },
   {
    "t": 91080,
    "d": 7,
    "l": 0,
    "p": []
   },
   {
    "t": 91200,
    "d": 5,
    "l": 0,
    "p": []
   },
   {
    "t": 91200,
    "d": 2,
    "l": 270,
    "p": []
   },
   {
    "t": 91320,
    "d": 7,
    "l": 0,
    "p": []
   },
   {
    "t": 91440,
    "d": 5,
    "l": 0,
    "p": []
   },
   {
    "t": 91560,
    "d": 6,
    "l": 0,
    "p": []
   },
   {
    "t": 91680,
    "d": 4,
    "l": 0,
    "p": []
   },
   {
    "t": 91680,
    "d": 3,
    "l": 0,
    "p": []
   },
   {
    "t": 91800,
    "d": 5,
    "l": 0,
    "p": []
   },
   {
    "t": 91800,
    "d": 0,
    "l": 0,
    "p": []
   },
   {
    "t": 91920,
    "d": 7,
    "l": 0,
    "p": []
   },
   {
    "t": 91920,
    "d": 1,
    "l": 0,
    "p": []
   },
   {
    "t": 92040,
    "d": 4,
    "l": 0,
    "p": []
   },
   {
    "t": 92040,
    "d": 3,
    "l": 0,
    "p": []
   },
   {
    "t": 92160,
    "d": 7,
    "l": 1020,
    "p": []
   },
   {
    "t": 92160,
    "d": 0,
    "l": 1020,
    "p": []
   },
   {
    "t": 93600,
    "d": 3,
    "l": 0,
    "p": []
   },
   {
    "t": 93600,
    "d": 4,
    "l": 390,
    "p": []
   },
   {
    "t": 93630,
    "d": 2,
    "l": 240,
    "p": []
   },
   {
    "t": 94080,
    "d": 0,
    "l": 510,
    "p": []
   },
   {
    "t": 94080,
    "d": 6,
    "l": 0,
    "p": []
   },
   {
    "t": 94560,
    "d": 4,
    "l": 0,
    "p": []
   },
   {
    "t": 94800,
    "d": 2,
    "l": 510,
    "p": []
   },
   {
    "t": 94800,
    "d": 5,
    "l": 0,
    "p": []
   },
   {
    "t": 94800,
    "d": 7,
    "l": 0,
    "p": []
   },
   {
    "t": 95280,
    "d": 4,
    "l": 0,
    "p": []
   },
   {
    "t": 95520,
    "d": 3,
    "l": 0,
    "p": []
   },
   {
    "t": 95520,
    "d": 6,
    "l": 270,
    "p": []
   },
   {
    "t": 95640,
    "d": 1,
    "l": 0,
    "p": []
   },
   {
    "t": 95760,
    "d": 2,
    "l": 0,
    "p": []
   },
   {
    "t": 96000,
    "d": 0,
    "l": 0,
    "p": []
   },
   {
    "t": 96000,
    "d": 6,
    "l": 270,
    "p": []
   },
   {
    "t": 96240,
    "d": 3,
    "l": 0,
    "p": []
   },
   {
    "t": 96360,
    "d": 0,
    "l": 0,
    "p": []
   },
   {
    "t": 96480,
    "d": 1,
    "l": 0,
    "p": []
   },
   {
    "t": 96480,
    "d": 4,
    "l": 390,
    "p": []
   },
   {
    "t": 96600,
    "d": 3,
    "l": 0,
    "p": []
   },
   {
    "t": 96720,
    "d": 1,
    "l": 0,
    "p": []
   },
   {
    "t": 96840,
    "d": 0,
    "l": 0,
    "p": []
   },
   {
    "t": 96960,
    "d": 2,
    "l": 0,
    "p": []
   },
   {
    "t": 96960,
    "d": 5,
    "l": 390,
    "p": []
   },
   {
    "t": 97080,
    "d": 0,
    "l": 0,
    "p": []
   },
   {
    "t": 97200,
    "d": 3,
    "l": 0,
    "p": []
   },
   {
    "t": 97320,
    "d": 1,
    "l": 0,
    "p": []
   },
   {
    "t": 97440,
    "d": 3,
    "l": 0,
    "p": []
   },
   {
    "t": 97440,
    "d": 7,
    "l": 390,
    "p": []
   },
   {
    "t": 97560,
    "d": 0,
    "l": 0,
    "p": []
   },
   {
    "t": 97680,
    "d": 2,
    "l": 0,
    "p": []
   },
   {
    "t": 97800,
    "d": 1,
    "l": 0,
    "p": []
   },
   {
    "t": 97920,
    "d": 2,
    "l": 0,
    "p": []
   },
   {
    "t": 97920,
    "d": 6,
    "l": 390,
    "p": []
   },
   {
    "t": 98160,
    "d": 3,
    "l": 0,
    "p": []
   },
   {
    "t": 98280,
    "d": 0,
    "l": 0,
    "p": []
   },
   {
    "t": 98400,
    "d": 1,
    "l": 0,
    "p": []
   },
   {
    "t": 98400,
    "d": 4,
    "l": 390,
    "p": []
   },
   {
    "t": 98520,
    "d": 2,
    "l": 0,
    "p": []
   },
   {
    "t": 98640,
    "d": 0,
    "l": 0,
    "p": []
   },
   {
    "t": 98760,
    "d": 3,
    "l": 0,
    "p": []
   },
   {
    "t": 98880,
    "d": 1,
    "l": 0,
    "p": []
   },
   {
    "t": 98880,
    "d": 6,
    "l": 390,
    "p": []
   },
   {
    "t": 99000,
    "d": 2,
    "l": 0,
    "p": []
   },
   {
    "t": 99120,
    "d": 0,
    "l": 0,
    "p": []
   },
   {
    "t": 99240,
    "d": 3,
    "l": 0,
    "p": []
   },
   {
    "t": 99360,
    "d": 1,
    "l": 0,
    "p": []
   },
   {
    "t": 99360,
    "d": 5,
    "l": 390,
    "p": []
   },
   {
    "t": 99480,
    "d": 3,
    "l": 0,
    "p": []
   },
   {
    "t": 99600,
    "d": 1,
    "l": 0,
    "p": []
   },
   {
    "t": 99720,
    "d": 2,
    "l": 0,
    "p": []
   },
   {
    "t": 99840,
    "d": 0,
    "l": 870,
    "p": []
   },
   {
    "t": 99840,
    "d": 7,
    "l": 870,
    "p": []
   }
  ],
  "normal": []
 },
 "generatedBy": "Friday Night Funkin' - v0.8.0"
}