{
 "version": "2.0.0",
 "scrollSpeed": {
  "easy": 1,
  "normal": 1,
  "hard": 2.4
 },
 "events": [
  {
   "t": 0,
   "e": "FocusCamera",
   "v": {
	"duration": 4,
	"x": 0,
	"y": 0,
	"ease": "INSTANT",
	"char": 0,
	"easeDir": "In"
}
  },
  {
   "t": 416.666666666667,
   "e": "FocusCamera",
   "v": {
	"duration": 4,
	"x": 0,
	"y": 0,
	"ease": "INSTANT",
	"char": 2,
	"easeDir": "In"
}
  },
  {
   "t": 833.333333333333,
   "e": "FocusCamera",
   "v": {
	"duration": 4,
	"x": 0,
	"y": 0,
	"ease": "INSTANT",
	"char": 1,
	"easeDir": "In"
}
  },
  {
   "t": 1250,
   "e": "FocusCamera",
   "v": {
	"duration": 4,
	"x": 0,
	"y": 0,
	"ease": "INSTANT",
	"char": 0,
	"easeDir": "In"
}
  },
  {
   "t": 1666.66666666667,
   "e": "FocusCamera",
   "v": {
	"char": 1
}
  },
  {
   "t": 4999.66666666667,
   "e": "FocusCamera",
   "v": {
	"char": 0
}
  },
  {
   "t": 8332.66666666667,
   "e": "FocusCamera",
   "v": {
	"char": 1
}
  },
  {
   "t": 9999.66666666667,
   "e": "FocusCamera",
   "v": {
	"char": 0
}
  },
  {
   "t": 11666.6666666667,
   "e": "FocusCamera",
   "v": {
	"char": 1
}
  },
  {
   "t": 13332.6666666667,
   "e": "FocusCamera",
   "v": {
	"char": 0
}
  },
  {
   "t": 15416.6666666667,
   "e": "FocusCamera",
   "v": {
	"char": 1
}
  },
  {
   "t": 21666.6666666667,
   "e": "FocusCamera",
   "v": {
	"char": 0
}
  },
  {
   "t": 28332.6666666667,
   "e": "FocusCamera",
   "v": {
	"char": 1
}
  },
  {
   "t": 29999.6666666667,
   "e": "FocusCamera",
   "v": {
	"char": 0
}
  },
  {
   "t": 31666.6666666667,
   "e": "FocusCamera",
   "v": {
	"char": 1
}
  },
  {
   "t": 33332.6666666667,
   "e": "FocusCamera",
   "v": {
	"char": 0
}
  },
  {
   "t": 41666.6666666667,
   "e": "FocusCamera",
   "v": {
	"char": 1
}
  },
  {
   "t": 48332.6666666667,
   "e": "FocusCamera",
   "v": {
	"char": 0
}
  },
  {
   "t": 54999.6666666667,
   "e": "FocusCamera",
   "v": {
	"char": 1
}
  },
  {
   "t": 58332.6666666667,
   "e": "FocusCamera",
   "v": {
	"char": 0
}
  },
  {
   "t": 61666.6666666667,
   "e": "FocusCamera",
   "v": {
	"char": 1
}
  },
  {
   "t": 63332.6666666667,
   "e": "FocusCamera",
   "v": {
	"char": 0
}
  },
  {
   "t": 64999.6666666667,
   "e": "FocusCamera",
   "v": {
	"char": 1
}
  },
  {
   "t": 66666.6666666667,
   "e": "FocusCamera",
   "v": {
	"char": 0
}
  },
  {
   "t": 68332.6666666667,
   "e": "FocusCamera",
   "v": {
	"char": 1
}
  },
  {
   "t": 71666.6666666667,
   "e": "FocusCamera",
   "v": {
	"char": 0
}
  },
  {
   "t": 74999.6666666667,
   "e": "FocusCamera",
   "v": {
	"char": 1
}
  },
  {
   "t": 78332.6666666667,
   "e": "FocusCamera",
   "v": {
	"char": 0
}
  },
  {
   "t": 81666.6666666667,
   "e": "FocusCamera",
   "v": {
	"char": 1
}
  },
  {
   "t": 88332.6666666667,
   "e": "FocusCamera",
   "v": {
	"char": 0
}
  },
  {
   "t": 96979.1666666667,
   "e": "PlayAnimation",
   "v": {
	"force": true,
	"anim": "hey!",
	"target": "boyfriend"
}
  }
 ],
 "notes": {
  "easy": [],
  "normal": [],
  "hard": [
   {
    "t": 1666.66666666667,
    "d": 4,
    "l": 260.416666666667
   },
   {
    "t": 2083.33333333333,
    "d": 7
   },
   {
    "t": 2291.66666666667,
    "d": 6
   },
   {
    "t": 2500,
    "d": 4,
    "l": 338.541666666667
   },
   {
    "t": 2916.66666666667,
    "d": 5,
    "l": 338.541666666667
   },
   {
    "t": 3333.33333333333,
    "d": 6,
    "l": 442.708333333333
   },
   {
    "t": 3958.33333333333,
    "d": 7,
    "l": 937.500000000001
   },
   {
    "t": 5000,
    "d": 3
   },
   {
    "t": 5416.66666666667,
    "d": 1
   },
   {
    "t": 5625,
    "d": 3
   },
   {
    "t": 5833.33333333333,
    "d": 2
   },
   {
    "t": 5833.33333333333,
    "d": 0
   },
   {
    "t": 6041.66666666667,
    "d": 1
   },
   {
    "t": 6250,
    "d": 2,
    "l": 156.25
   },
   {
    "t": 6458.33333333333,
    "d": 1
   },
   {
    "t": 6666.66666666667,
    "d": 3
   },
   {
    "t": 6875,
    "d": 0
   },
   {
    "t": 7083.33333333333,
    "d": 2
   },
   {
    "t": 7291.66666666667,
    "d": 3
   },
   {
    "t": 7317.70833333333,
    "d": 1,
    "l": 312.5
   },
   {
    "t": 7708.33333333333,
    "d": 0
   },
   {
    "t": 7916.66666666667,
    "d": 1
   },
   {
    "t": 8125,
    "d": 2
   },
   {
    "t": 8333.33333333333,
    "d": 1,
    "l": 234.375
   },
   {
    "t": 8333.33333333333,
    "d": 5,
    "l": 234.375
   },
   {
    "t": 8750,
    "d": 3
   },
   {
    "t": 8750,
    "d": 4
   },
   {
    "t": 8958.33333333333,
    "d": 2
   },
   {
    "t": 8958.33333333333,
    "d": 7
   },
   {
    "t": 9166.66666666667,
    "d": 0,
    "l": 130.208333333332
   },
   {
    "t": 9166.66666666667,
    "d": 6,
    "l": 338.541666666665
   },
   {
    "t": 9375,
    "d": 3
   },
   {
    "t": 9583.33333333333,
    "d": 0
   },
   {
    "t": 9583.33333333333,
    "d": 5,
    "l": 338.541666666667
   },
   {
    "t": 9609.375,
    "d": 2
   },
   {
    "t": 9791.66666666667,
    "d": 1
   },
   {
    "t": 10000,
    "d": 3
   },
   {
    "t": 10000,
    "d": 7,
    "l": 338.541666666668
   },
   {
    "t": 10208.3333333333,
    "d": 2
   },
   {
    "t": 10416.6666666667,
    "d": 1
   },
   {
    "t": 10416.6666666667,
    "d": 5
   },
   {
    "t": 10625,
    "d": 0
   },
   {
    "t": 10625,
    "d": 6,
    "l": 234.375
   },
   {
    "t": 10651.0416666667,
    "d": 2
   },
   {
    "t": 10833.3333333333,
    "d": 3
   },
   {
    "t": 11041.6666666667,
    "d": 1
   },
   {
    "t": 11041.6666666667,
    "d": 5
   },
   {
    "t": 11250,
    "d": 2
   },
   {
    "t": 11250,
    "d": 6,
    "l": 234.375
   },
   {
    "t": 11458.3333333333,
    "d": 1
   },
   {
    "t": 11666.6666666667,
    "d": 3
   },
   {
    "t": 11666.6666666667,
    "d": 5
   },
   {
    "t": 12083.3333333333,
    "d": 1,
    "l": 234.375
   },
   {
    "t": 12083.3333333333,
    "d": 7
   },
   {
    "t": 12109.375,
    "d": 4,
    "l": 312.5
   },
   {
    "t": 12500,
    "d": 3
   },
   {
    "t": 12500,
    "d": 6
   },
   {
    "t": 12708.3333333333,
    "d": 1
   },
   {
    "t": 12708.3333333333,
    "d": 5
   },
   {
    "t": 12916.6666666667,
    "d": 2,
    "l": 130.208333333333
   },
   {
    "t": 12916.6666666667,
    "d": 7,
    "l": 338.541666666667
   },
   {
    "t": 13333.3333333333,
    "d": 0
   },
   {
    "t": 13333.3333333333,
    "d": 4
   },
   {
    "t": 13541.6666666667,
    "d": 3
   },
   {
    "t": 13541.6666666667,
    "d": 5
   },
   {
    "t": 13750,
    "d": 1
   },
   {
    "t": 13750,
    "d": 6
   },
   {
    "t": 13776.0416666667,
    "d": 0,
    "l": 104.166666666667
   },
   {
    "t": 13958.3333333333,
    "d": 3
   },
   {
    "t": 13958.3333333333,
    "d": 7
   },
   {
    "t": 14166.6666666667,
    "d": 2,
    "l": 338.541666666667
   },
   {
    "t": 14166.6666666667,
    "d": 6
   },
   {
    "t": 14375,
    "d": 5
   },
   {
    "t": 14583.3333333333,
    "d": 3,
    "l": 338.541666666667
   },
   {
    "t": 14583.3333333333,
    "d": 4
   },
   {
    "t": 14791.6666666667,
    "d": 7
   },
   {
    "t": 14791.6666666667,
    "d": 5
   },
   {
    "t": 15000,
    "d": 1,
    "l": 1380.20833333333
   },
   {
    "t": 15416.6666666667,
    "d": 6,
    "l": 312.5
   },
   {
    "t": 15833.3333333333,
    "d": 4
   },
   {
    "t": 15859.375,
    "d": 5,
    "l": 416.666666666667
   },
   {
    "t": 16457.6666666667,
    "d": 7,
    "l": 625
   },
   {
    "t": 17291.6666666667,
    "d": 4
   },
   {
    "t": 17343.75,
    "d": 5
   },
   {
    "t": 17395.8333333333,
    "d": 7
   },
   {
    "t": 17682.2916666667,
    "d": 4
   },
   {
    "t": 17916.6666666667,
    "d": 5,
    "l": 234.375
   },
   {
    "t": 18333.3333333333,
    "d": 4,
    "l": 234.375
   },
   {
    "t": 18750,
    "d": 7
   },
   {
    "t": 18958.3333333333,
    "d": 6,
    "l": 364.58333333333
   },
   {
    "t": 19375,
    "d": 5,
    "l": 338.541666666667
   },
   {
    "t": 19791.6666666667,
    "d": 6
   },
   {
    "t": 20208.3333333333,
    "d": 4
   },
   {
    "t": 20625,
    "d": 6,
    "l": 573.250000000002
   },
   {
    "t": 21249.6666666667,
    "d": 7,
    "l": 364.916666666669
   },
   {
    "t": 21666.6666666667,
    "d": 5,
    "l": 364.583333333336
   },
   {
    "t": 22083.3333333333,
    "d": 2,
    "l": 338.541666666667
   },
   {
    "t": 22500,
    "d": 0,
    "l": 234.375
   },
   {
    "t": 22916.6666666667,
    "d": 3
   },
   {
    "t": 23125,
    "d": 0
   },
   {
    "t": 23125,
    "d": 1
   },
   {
    "t": 23958.3333333333,
    "d": 1
   },
   {
    "t": 23984.375,
    "d": 2,
    "l": 312.5
   },
   {
    "t": 24375,
    "d": 3
   },
   {
    "t": 24583.3333333333,
    "d": 2
   },
   {
    "t": 24791.6666666667,
    "d": 0
   },
   {
    "t": 25000,
    "d": 2
   },
   {
    "t": 25000,
    "d": 3
   },
   {
    "t": 25208.3333333333,
    "d": 1
   },
   {
    "t": 25416.6666666667,
    "d": 3
   },
   {
    "t": 25442.7083333333,
    "d": 0
   },
   {
    "t": 25468.75,
    "d": 2
   },
   {
    "t": 25625,
    "d": 1,
    "l": 234.375
   },
   {
    "t": 26041.6666666667,
    "d": 0
   },
   {
    "t": 26067.7083333333,
    "d": 2
   },
   {
    "t": 26250,
    "d": 3
   },
   {
    "t": 26458.3333333333,
    "d": 1
   },
   {
    "t": 26875,
    "d": 0
   },
   {
    "t": 26979.1666666667,
    "d": 3
   },
   {
    "t": 27083.3333333333,
    "d": 2
   },
   {
    "t": 27291.6666666667,
    "d": 1
   },
   {
    "t": 27500,
    "d": 0,
    "l": 130.208333333333
   },
   {
    "t": 27708.3333333333,
    "d": 2
   },
   {
    "t": 27916.6666666667,
    "d": 3,
    "l": 156.25
   },
   {
    "t": 28125,
    "d": 1
   },
   {
    "t": 28332.6666666667,
    "d": 4
   },
   {
    "t": 28333.3333333333,
    "d": 0,
    "l": 859.375
   },
   {
    "t": 28436.6666666667,
    "d": 7
   },
   {
    "t": 28541.6666666667,
    "d": 5
   },
   {
    "t": 28645.6666666667,
    "d": 7
   },
   {
    "t": 28749.6666666667,
    "d": 4
   },
   {
    "t": 28957.6666666667,
    "d": 5
   },
   {
    "t": 29166.6666666667,
    "d": 6
   },
   {
    "t": 29375,
    "d": 2
   },
   {
    "t": 29375,
    "d": 5
   },
   {
    "t": 29582.6666666667,
    "d": 7
   },
   {
    "t": 29791.6666666667,
    "d": 1
   },
   {
    "t": 29791.6666666667,
    "d": 6
   },
   {
    "t": 29999.6666666667,
    "d": 7,
    "l": 208
   },
   {
    "t": 30208.3333333333,
    "d": 0
   },
   {
    "t": 30416.6666666667,
    "d": 2
   },
   {
    "t": 30416.6666666667,
    "d": 4,
    "l": 364.583333333333
   },
   {
    "t": 30625,
    "d": 3
   },
   {
    "t": 30832.6666666667,
    "d": 6
   },
   {
    "t": 30833.3333333333,
    "d": 0
   },
   {
    "t": 30937.5,
    "d": 1
   },
   {
    "t": 31041.6666666667,
    "d": 7
   },
   {
    "t": 31041.6666666667,
    "d": 2
   },
   {
    "t": 31250,
    "d": 0
   },
   {
    "t": 31250,
    "d": 5,
    "l": 312
   },
   {
    "t": 31458.3333333333,
    "d": 1
   },
   {
    "t": 31666.6666666667,
    "d": 7
   },
   {
    "t": 31666.6666666667,
    "d": 3
   },
   {
    "t": 31875,
    "d": 1
   },
   {
    "t": 32082.6666666667,
    "d": 5
   },
   {
    "t": 32083.3333333333,
    "d": 2
   },
   {
    "t": 32083.3333333333,
    "d": 4
   },
   {
    "t": 32291.6666666667,
    "d": 3
   },
   {
    "t": 32291.6666666667,
    "d": 6,
    "l": 755.208333333333
   },
   {
    "t": 32500,
    "d": 1
   },
   {
    "t": 32708.3333333333,
    "d": 3
   },
   {
    "t": 32916.6666666667,
    "d": 0
   },
   {
    "t": 32916.6666666667,
    "d": 1
   },
   {
    "t": 33124.6666666667,
    "d": 7,
    "l": 573.249999999999
   },
   {
    "t": 33125,
    "d": 2
   },
   {
    "t": 33541.6666666667,
    "d": 1
   },
   {
    "t": 33749.6666666667,
    "d": 5
   },
   {
    "t": 33750,
    "d": 3
   },
   {
    "t": 33957.6666666667,
    "d": 7
   },
   {
    "t": 33958.3333333333,
    "d": 0,
    "l": 130.208333333339
   },
   {
    "t": 34166.6666666667,
    "d": 7
   },
   {
    "t": 34166.6666666667,
    "d": 3
   },
   {
    "t": 34270.8333333333,
    "d": 1
   },
   {
    "t": 34374.6666666667,
    "d": 4
   },
   {
    "t": 34375,
    "d": 2
   },
   {
    "t": 34582.6666666667,
    "d": 5,
    "l": 208
   },
   {
    "t": 34583.3333333333,
    "d": 0
   },
   {
    "t": 34791.6666666667,
    "d": 2
   },
   {
    "t": 35000,
    "d": 3
   },
   {
    "t": 35000,
    "d": 6,
    "l": 338.541666666673
   },
   {
    "t": 35104.1666666667,
    "d": 1
   },
   {
    "t": 35208.3333333333,
    "d": 3
   },
   {
    "t": 35312.5,
    "d": 0
   },
   {
    "t": 35416.6666666667,
    "d": 2
   },
   {
    "t": 35416.6666666667,
    "d": 4
   },
   {
    "t": 35625,
    "d": 3
   },
   {
    "t": 35625,
    "d": 5
   },
   {
    "t": 35833.3333333333,
    "d": 1,
    "l": 130.208333333339
   },
   {
    "t": 36041.6666666667,
    "d": 2
   },
   {
    "t": 36250,
    "d": 0
   },
   {
    "t": 36250,
    "d": 4
   },
   {
    "t": 36302.0833333333,
    "d": 6
   },
   {
    "t": 36458.3333333333,
    "d": 2
   },
   {
    "t": 36458.3333333333,
    "d": 5
   },
   {
    "t": 36666.6666666667,
    "d": 3,
    "l": 234.375
   },
   {
    "t": 37083.3333333333,
    "d": 1,
    "l": 234.375
   },
   {
    "t": 37083.3333333333,
    "d": 4
   },
   {
    "t": 37135.4166666667,
    "d": 6
   },
   {
    "t": 37291.6666666667,
    "d": 5
   },
   {
    "t": 37500,
    "d": 0
   },
   {
    "t": 37708.3333333333,
    "d": 1
   },
   {
    "t": 37916.6666666667,
    "d": 2,
    "l": 234.375
   },
   {
    "t": 37916.6666666667,
    "d": 4
   },
   {
    "t": 37942.7083333333,
    "d": 6
   },
   {
    "t": 38125,
    "d": 5
   },
   {
    "t": 38333.3333333333,
    "d": 0
   },
   {
    "t": 38333.3333333333,
    "d": 4,
    "l": 338.541666666667
   },
   {
    "t": 38750,
    "d": 2
   },
   {
    "t": 38750,
    "d": 7
   },
   {
    "t": 38802.0833333333,
    "d": 6
   },
   {
    "t": 38958.3333333333,
    "d": 1
   },
   {
    "t": 38958.3333333333,
    "d": 5
   },
   {
    "t": 39166.6666666667,
    "d": 0
   },
   {
    "t": 39270.8333333333,
    "d": 2
   },
   {
    "t": 39375,
    "d": 3
   },
   {
    "t": 39479.1666666667,
    "d": 1
   },
   {
    "t": 39583.3333333333,
    "d": 0
   },
   {
    "t": 39583.3333333333,
    "d": 4
   },
   {
    "t": 39635.4166666667,
    "d": 6
   },
   {
    "t": 39791.6666666667,
    "d": 2,
    "l": 130.208333333327
   },
   {
    "t": 39791.6666666667,
    "d": 5
   },
   {
    "t": 40208.3333333333,
    "d": 3
   },
   {
    "t": 40312.5,
    "d": 1
   },
   {
    "t": 40416.6666666667,
    "d": 2
   },
   {
    "t": 40416.6666666667,
    "d": 7
   },
   {
    "t": 40442.7083333333,
    "d": 0
   },
   {
    "t": 40442.7083333333,
    "d": 4
   },
   {
    "t": 40625,
    "d": 1
   },
   {
    "t": 40625,
    "d": 5
   },
   {
    "t": 40833.3333333333,
    "d": 2
   },
   {
    "t": 40833.3333333333,
    "d": 7,
    "l": 338.541666666667
   },
   {
    "t": 40859.375,
    "d": 3
   },
   {
    "t": 41041.6666666667,
    "d": 0
   },
   {
    "t": 41250,
    "d": 1
   },
   {
    "t": 41458.3333333333,
    "d": 3
   },
   {
    "t": 41666.6666666667,
    "d": 6,
    "l": 364.583333333333
   },
   {
    "t": 41666.6666666667,
    "d": 1,
    "l": 651.041666666667
   },
   {
    "t": 42082.6666666667,
    "d": 4
   },
   {
    "t": 42186.6666666667,
    "d": 5
   },
   {
    "t": 42291.6666666667,
    "d": 4
   },
   {
    "t": 42395.6666666667,
    "d": 5
   },
   {
    "t": 42499.6666666667,
    "d": 7,
    "l": 364.916666666672
   },
   {
    "t": 42916.6666666667,
    "d": 5
   },
   {
    "t": 43124.6666666667,
    "d": 4,
    "l": 781.583333333333
   },
   {
    "t": 43957.6666666667,
    "d": 5,
    "l": 365.250000000004
   },
   {
    "t": 44374.6666666667,
    "d": 7,
    "l": 364.916666666666
   },
   {
    "t": 44791.6666666667,
    "d": 4
   },
   {
    "t": 45000,
    "d": 5,
    "l": 364.916666666666
   },
   {
    "t": 45416.6666666667,
    "d": 7
   },
   {
    "t": 45624.6666666667,
    "d": 6,
    "l": 364.916666666666
   },
   {
    "t": 46041.6666666667,
    "d": 4
   },
   {
    "t": 46145.8333333333,
    "d": 7
   },
   {
    "t": 46249.6666666667,
    "d": 6
   },
   {
    "t": 46457.6666666667,
    "d": 4
   },
   {
    "t": 46666.6666666667,
    "d": 6,
    "l": 130.208333333333
   },
   {
    "t": 46875,
    "d": 7
   },
   {
    "t": 46978.6666666667,
    "d": 4
   },
   {
    "t": 47083.3333333333,
    "d": 6
   },
   {
    "t": 47291.6666666667,
    "d": 5
   },
   {
    "t": 47499.6666666667,
    "d": 7
   },
   {
    "t": 47707.6666666667,
    "d": 6
   },
   {
    "t": 47916.6666666667,
    "d": 7
   },
   {
    "t": 47968.75,
    "d": 5
   },
   {
    "t": 48020.8333333333,
    "d": 6
   },
   {
    "t": 48125,
    "d": 4,
    "l": 130.208333333333
   },
   {
    "t": 48333.3333333333,
    "d": 2,
    "l": 234.375
   },
   {
    "t": 48750,
    "d": 0
   },
   {
    "t": 48854.1666666667,
    "d": 1
   },
   {
    "t": 48958.3333333333,
    "d": 2
   },
   {
    "t": 49062.5,
    "d": 0
   },
   {
    "t": 49166.6666666667,
    "d": 3,
    "l": 130.208333333333
   },
   {
    "t": 49375,
    "d": 2
   },
   {
    "t": 49583.3333333333,
    "d": 0
   },
   {
    "t": 49609.375,
    "d": 3
   },
   {
    "t": 49791.6666666667,
    "d": 2
   },
   {
    "t": 50000,
    "d": 1
   },
   {
    "t": 50416.6666666667,
    "d": 0
   },
   {
    "t": 50520.8333333333,
    "d": 3
   },
   {
    "t": 50625,
    "d": 2
   },
   {
    "t": 51041.6666666667,
    "d": 2
   },
   {
    "t": 51145.8333333333,
    "d": 3
   },
   {
    "t": 51250,
    "d": 0
   },
   {
    "t": 51276.0416666667,
    "d": 1,
    "l": 104.166666666667
   },
   {
    "t": 51458.3333333333,
    "d": 2
   },
   {
    "t": 51666.6666666667,
    "d": 3
   },
   {
    "t": 51875,
    "d": 2
   },
   {
    "t": 51979.1666666667,
    "d": 0
   },
   {
    "t": 52083.3333333333,
    "d": 1
   },
   {
    "t": 52291.6666666667,
    "d": 2
   },
   {
    "t": 52317.7083333333,
    "d": 3
   },
   {
    "t": 52500,
    "d": 1
   },
   {
    "t": 52708.3333333333,
    "d": 3
   },
   {
    "t": 52916.6666666667,
    "d": 2
   },
   {
    "t": 52942.7083333333,
    "d": 0
   },
   {
    "t": 52994.7916666667,
    "d": 1
   },
   {
    "t": 53125,
    "d": 3
   },
   {
    "t": 53333.3333333333,
    "d": 2
   },
   {
    "t": 53541.6666666667,
    "d": 0
   },
   {
    "t": 53645.8333333333,
    "d": 3
   },
   {
    "t": 53750,
    "d": 1
   },
   {
    "t": 53932.2916666667,
    "d": 0
   },
   {
    "t": 53958.3333333333,
    "d": 3
   },
   {
    "t": 54166.6666666667,
    "d": 1
   },
   {
    "t": 54375,
    "d": 3,
    "l": 546.875
   },
   {
    "t": 55000,
    "d": 4,
    "l": 260.416666666667
   },
   {
    "t": 55416.6666666667,
    "d": 1,
    "l": 755.208333333333
   },
   {
    "t": 55416.6666666667,
    "d": 7
   },
   {
    "t": 55625,
    "d": 6
   },
   {
    "t": 55833.3333333333,
    "d": 4,
    "l": 338.541666666667
   },
   {
    "t": 56250,
    "d": 5,
    "l": 338.541666666667
   },
   {
    "t": 56666.6666666667,
    "d": 6,
    "l": 442.708333333333
   },
   {
    "t": 57291.6666666667,
    "d": 7,
    "l": 937.500000000001
   },
   {
    "t": 58333.3333333333,
    "d": 2,
    "l": 234.375
   },
   {
    "t": 58750,
    "d": 1
   },
   {
    "t": 58958.3333333333,
    "d": 3
   },
   {
    "t": 59166.6666666667,
    "d": 2
   },
   {
    "t": 59166.6666666667,
    "d": 0
   },
   {
    "t": 59375,
    "d": 1
   },
   {
    "t": 59583.3333333333,
    "d": 2,
    "l": 156.25
   },
   {
    "t": 59791.6666666667,
    "d": 1
   },
   {
    "t": 60000,
    "d": 3
   },
   {
    "t": 60208.3333333333,
    "d": 0
   },
   {
    "t": 60416.6666666667,
    "d": 2
   },
   {
    "t": 60625,
    "d": 3
   },
   {
    "t": 60651.0416666667,
    "d": 1,
    "l": 312.5
   },
   {
    "t": 61041.6666666667,
    "d": 0
   },
   {
    "t": 61250,
    "d": 1
   },
   {
    "t": 61458.3333333333,
    "d": 2
   },
   {
    "t": 61666.6666666667,
    "d": 1,
    "l": 234.375
   },
   {
    "t": 61666.6666666667,
    "d": 5,
    "l": 234.375
   },
   {
    "t": 62083.3333333333,
    "d": 3
   },
   {
    "t": 62083.3333333333,
    "d": 4
   },
   {
    "t": 62291.6666666667,
    "d": 2
   },
   {
    "t": 62291.6666666667,
    "d": 7
   },
   {
    "t": 62500,
    "d": 0,
    "l": 130.208333333332
   },
   {
    "t": 62500,
    "d": 6,
    "l": 338.541666666665
   },
   {
    "t": 62708.3333333333,
    "d": 3
   },
   {
    "t": 62916.6666666667,
    "d": 0
   },
   {
    "t": 62916.6666666667,
    "d": 5,
    "l": 338.541666666667
   },
   {
    "t": 62942.7083333333,
    "d": 2
   },
   {
    "t": 63125,
    "d": 1
   },
   {
    "t": 63333.3333333333,
    "d": 3
   },
   {
    "t": 63333.3333333333,
    "d": 7,
    "l": 338.541666666668
   },
   {
    "t": 63541.6666666667,
    "d": 2
   },
   {
    "t": 63750,
    "d": 1
   },
   {
    "t": 63750,
    "d": 5
   },
   {
    "t": 63958.3333333333,
    "d": 0
   },
   {
    "t": 63958.3333333333,
    "d": 6,
    "l": 234.375
   },
   {
    "t": 63984.375,
    "d": 2
   },
   {
    "t": 64166.6666666667,
    "d": 3
   },
   {
    "t": 64375,
    "d": 1
   },
   {
    "t": 64375,
    "d": 5
   },
   {
    "t": 64583.3333333333,
    "d": 2
   },
   {
    "t": 64583.3333333333,
    "d": 6,
    "l": 234.375
   },
   {
    "t": 64791.6666666667,
    "d": 1
   },
   {
    "t": 65000,
    "d": 3
   },
   {
    "t": 65000,
    "d": 5
   },
   {
    "t": 65416.6666666667,
    "d": 1,
    "l": 234.375
   },
   {
    "t": 65416.6666666667,
    "d": 7
   },
   {
    "t": 65442.7083333333,
    "d": 4,
    "l": 312.5
   },
   {
    "t": 65833.3333333333,
    "d": 3
   },
   {
    "t": 65833.3333333333,
    "d": 6
   },
   {
    "t": 66041.6666666667,
    "d": 1
   },
   {
    "t": 66041.6666666667,
    "d": 5
   },
   {
    "t": 66250,
    "d": 2,
    "l": 130.208333333333
   },
   {
    "t": 66250,
    "d": 7,
    "l": 338.541666666667
   },
   {
    "t": 66666.6666666667,
    "d": 0
   },
   {
    "t": 66666.6666666667,
    "d": 4
   },
   {
    "t": 66875,
    "d": 3
   },
   {
    "t": 66875,
    "d": 5
   },
   {
    "t": 67083.3333333333,
    "d": 1
   },
   {
    "t": 67083.3333333333,
    "d": 6
   },
   {
    "t": 67109.375,
    "d": 0,
    "l": 104.166666666667
   },
   {
    "t": 67291.6666666667,
    "d": 3
   },
   {
    "t": 67291.6666666667,
    "d": 7
   },
   {
    "t": 67500,
    "d": 2,
    "l": 338.541666666667
   },
   {
    "t": 67500,
    "d": 6
   },
   {
    "t": 67708.3333333333,
    "d": 5
   },
   {
    "t": 67916.6666666667,
    "d": 3,
    "l": 338.541666666667
   },
   {
    "t": 67916.6666666667,
    "d": 4
   },
   {
    "t": 68125,
    "d": 7
   },
   {
    "t": 68125,
    "d": 5
   },
   {
    "t": 68333.3333333333,
    "d": 1,
    "l": 1380.20833333332
   },
   {
    "t": 68333.3333333333,
    "d": 4
   },
   {
    "t": 68541.6666666667,
    "d": 6
   },
   {
    "t": 68750,
    "d": 5
   },
   {
    "t": 68958.3333333333,
    "d": 6
   },
   {
    "t": 69166.6666666667,
    "d": 4
   },
   {
    "t": 69374.6666666667,
    "d": 7
   },
   {
    "t": 69583.3333333333,
    "d": 6
   },
   {
    "t": 69791.6666666667,
    "d": 5
   },
   {
    "t": 69791.6666666667,
    "d": 7
   },
   {
    "t": 70000,
    "d": 4
   },
   {
    "t": 70207.6666666667,
    "d": 7
   },
   {
    "t": 70416.6666666667,
    "d": 6
   },
   {
    "t": 70625,
    "d": 5
   },
   {
    "t": 70832.6666666667,
    "d": 6
   },
   {
    "t": 71041.6666666667,
    "d": 7
   },
   {
    "t": 71249.6666666667,
    "d": 4
   },
   {
    "t": 71250,
    "d": 5,
    "l": 234.375
   },
   {
    "t": 71666.6666666667,
    "d": 1
   },
   {
    "t": 71875,
    "d": 2
   },
   {
    "t": 72083.3333333333,
    "d": 3
   },
   {
    "t": 72291.6666666667,
    "d": 1
   },
   {
    "t": 72500,
    "d": 2
   },
   {
    "t": 72500,
    "d": 0
   },
   {
    "t": 72708.3333333333,
    "d": 3
   },
   {
    "t": 72916.6666666667,
    "d": 0
   },
   {
    "t": 73125,
    "d": 1
   },
   {
    "t": 73333.3333333333,
    "d": 3
   },
   {
    "t": 73541.6666666667,
    "d": 1
   },
   {
    "t": 73750,
    "d": 3
   },
   {
    "t": 73958.3333333333,
    "d": 0
   },
   {
    "t": 74192.7083333333,
    "d": 2
   },
   {
    "t": 74375,
    "d": 0,
    "l": 338.541666666667
   },
   {
    "t": 74583.3333333333,
    "d": 5,
    "l": 130.208333333321
   },
   {
    "t": 74791.6666666667,
    "d": 2
   },
   {
    "t": 74791.6666666667,
    "d": 3
   },
   {
    "t": 74791.6666666667,
    "d": 7
   },
   {
    "t": 74999.6666666667,
    "d": 4
   },
   {
    "t": 75207.6666666667,
    "d": 7
   },
   {
    "t": 75208.3333333333,
    "d": 0
   },
   {
    "t": 75416.6666666667,
    "d": 5
   },
   {
    "t": 75624.6666666667,
    "d": 7
   },
   {
    "t": 75625,
    "d": 3
   },
   {
    "t": 75729.1666666667,
    "d": 4
   },
   {
    "t": 75833.3333333333,
    "d": 6
   },
   {
    "t": 76041.6666666667,
    "d": 7
   },
   {
    "t": 76249.6666666667,
    "d": 5
   },
   {
    "t": 76457.6666666667,
    "d": 7
   },
   {
    "t": 76561.6666666667,
    "d": 6
   },
   {
    "t": 76666.6666666667,
    "d": 4
   },
   {
    "t": 76874.6666666667,
    "d": 7
   },
   {
    "t": 77083.3333333333,
    "d": 4
   },
   {
    "t": 77291.6666666667,
    "d": 7
   },
   {
    "t": 77499.6666666667,
    "d": 6
   },
   {
    "t": 77682.2916666667,
    "d": 4
   },
   {
    "t": 77916.6666666667,
    "d": 6,
    "l": 234.375
   },
   {
    "t": 77916.6666666667,
    "d": 3
   },
   {
    "t": 78125,
    "d": 1
   },
   {
    "t": 78333.3333333333,
    "d": 2
   },
   {
    "t": 78541.6666666667,
    "d": 0
   },
   {
    "t": 78750,
    "d": 3
   },
   {
    "t": 78958.3333333333,
    "d": 1
   },
   {
    "t": 79062.5,
    "d": 0
   },
   {
    "t": 79166.6666666667,
    "d": 2
   },
   {
    "t": 79375,
    "d": 3
   },
   {
    "t": 79583.3333333333,
    "d": 0
   },
   {
    "t": 79635.4166666667,
    "d": 2
   },
   {
    "t": 79791.6666666667,
    "d": 1
   },
   {
    "t": 80000,
    "d": 0,
    "l": 130.208333333345
   },
   {
    "t": 80208.3333333333,
    "d": 2
   },
   {
    "t": 80416.6666666667,
    "d": 3
   },
   {
    "t": 80625,
    "d": 0
   },
   {
    "t": 80833.3333333333,
    "d": 2
   },
   {
    "t": 81041.6666666667,
    "d": 3,
    "l": 338.541666666679
   },
   {
    "t": 81458.3333333333,
    "d": 0
   },
   {
    "t": 81666.6666666667,
    "d": 7,
    "l": 364.583333333345
   },
   {
    "t": 81666.6666666667,
    "d": 1,
    "l": 755.208333333333
   },
   {
    "t": 82082.6666666667,
    "d": 4
   },
   {
    "t": 82186.6666666667,
    "d": 5
   },
   {
    "t": 82291.6666666667,
    "d": 6
   },
   {
    "t": 82395.8333333333,
    "d": 4
   },
   {
    "t": 82499.6666666667,
    "d": 7,
    "l": 364.916666666666
   },
   {
    "t": 82708.3333333333,
    "d": 3
   },
   {
    "t": 82916.6666666667,
    "d": 6
   },
   {
    "t": 83124.6666666667,
    "d": 4,
    "l": 781.583333333344
   },
   {
    "t": 83125,
    "d": 1
   },
   {
    "t": 83125,
    "d": 0
   },
   {
    "t": 83541.6666666667,
    "d": 3
   },
   {
    "t": 83750,
    "d": 0
   },
   {
    "t": 83958.3333333333,
    "d": 7,
    "l": 365.249999999998
   },
   {
    "t": 83958.3333333333,
    "d": 2
   },
   {
    "t": 84166.6666666667,
    "d": 1
   },
   {
    "t": 84270.8333333333,
    "d": 3
   },
   {
    "t": 84375,
    "d": 5,
    "l": 364.916666666666
   },
   {
    "t": 84375,
    "d": 0,
    "l": 130.208333333333
   },
   {
    "t": 84583.3333333333,
    "d": 2
   },
   {
    "t": 84791.6666666667,
    "d": 7
   },
   {
    "t": 84791.6666666667,
    "d": 1
   },
   {
    "t": 85000,
    "d": 6,
    "l": 364.916666666666
   },
   {
    "t": 85000,
    "d": 3
   },
   {
    "t": 85208.3333333333,
    "d": 0
   },
   {
    "t": 85416.6666666667,
    "d": 5
   },
   {
    "t": 85416.6666666667,
    "d": 1
   },
   {
    "t": 85625,
    "d": 7,
    "l": 364.916666666666
   },
   {
    "t": 85625,
    "d": 3
   },
   {
    "t": 85833.3333333333,
    "d": 1
   },
   {
    "t": 86041.6666666667,
    "d": 4
   },
   {
    "t": 86041.6666666667,
    "d": 0
   },
   {
    "t": 86145.8333333333,
    "d": 5
   },
   {
    "t": 86249.6666666667,
    "d": 6
   },
   {
    "t": 86250,
    "d": 3
   },
   {
    "t": 86250,
    "d": 2
   },
   {
    "t": 86458.3333333333,
    "d": 5
   },
   {
    "t": 86458.3333333333,
    "d": 0
   },
   {
    "t": 86666.6666666667,
    "d": 7
   },
   {
    "t": 86874.6666666667,
    "d": 5
   },
   {
    "t": 86875,
    "d": 3
   },
   {
    "t": 86978.6666666667,
    "d": 4
   },
   {
    "t": 87082.6666666667,
    "d": 7
   },
   {
    "t": 87083.3333333333,
    "d": 2,
    "l": 130.208333333333
   },
   {
    "t": 87291.6666666667,
    "d": 5
   },
   {
    "t": 87291.6666666667,
    "d": 0
   },
   {
    "t": 87499.6666666667,
    "d": 7
   },
   {
    "t": 87500,
    "d": 2
   },
   {
    "t": 87604.1666666667,
    "d": 3
   },
   {
    "t": 87707.6666666667,
    "d": 6
   },
   {
    "t": 87708.3333333333,
    "d": 0,
    "l": 130.208333333333
   },
   {
    "t": 87916.6666666667,
    "d": 7
   },
   {
    "t": 87916.6666666667,
    "d": 3
   },
   {
    "t": 88124.6666666667,
    "d": 4
   },
   {
    "t": 88125,
    "d": 1
   },
   {
    "t": 88333.3333333333,
    "d": 6
   },
   {
    "t": 88333.3333333333,
    "d": 2,
    "l": 312.5
   },
   {
    "t": 88541.6666666667,
    "d": 7
   },
   {
    "t": 88750,
    "d": 0
   },
   {
    "t": 88854.1666666667,
    "d": 1
   },
   {
    "t": 88958.3333333333,
    "d": 2
   },
   {
    "t": 89062.5,
    "d": 3
   },
   {
    "t": 89166.6666666667,
    "d": 0,
    "l": 156.25
   },
   {
    "t": 89375,
    "d": 4
   },
   {
    "t": 89375,
    "d": 1
   },
   {
    "t": 89583.3333333333,
    "d": 2
   },
   {
    "t": 89791.6666666667,
    "d": 7
   },
   {
    "t": 89791.6666666667,
    "d": 3
   },
   {
    "t": 90000,
    "d": 1
   },
   {
    "t": 90416.6666666667,
    "d": 7
   },
   {
    "t": 90416.6666666667,
    "d": 0
   },
   {
    "t": 90442.7083333333,
    "d": 4,
    "l": 234.375
   },
   {
    "t": 90520.8333333333,
    "d": 0
   },
   {
    "t": 90625,
    "d": 2
   },
   {
    "t": 90833.3333333333,
    "d": 5
   },
   {
    "t": 91041.6666666667,
    "d": 3
   },
   {
    "t": 91145.8333333333,
    "d": 3
   },
   {
    "t": 91250,
    "d": 6
   },
   {
    "t": 91250,
    "d": 0
   },
   {
    "t": 91276.0416666667,
    "d": 1
   },
   {
    "t": 91458.3333333333,
    "d": 5
   },
   {
    "t": 91458.3333333333,
    "d": 2
   },
   {
    "t": 91666.6666666667,
    "d": 7
   },
   {
    "t": 91666.6666666667,
    "d": 3
   },
   {
    "t": 91875,
    "d": 0
   },
   {
    "t": 91979.1666666667,
    "d": 3
   },
   {
    "t": 92083.3333333333,
    "d": 2
   },
   {
    "t": 92291.6666666667,
    "d": 0
   },
   {
    "t": 92500,
    "d": 5
   },
   {
    "t": 92500,
    "d": 1
   },
   {
    "t": 92708.3333333333,
    "d": 3
   },
   {
    "t": 92916.6666666667,
    "d": 2
   },
   {
    "t": 93020.8333333333,
    "d": 0
   },
   {
    "t": 93125,
    "d": 6
   },
   {
    "t": 93125,
    "d": 1
   },
   {
    "t": 93333.3333333333,
    "d": 3
   },
   {
    "t": 93541.6666666667,
    "d": 2
   },
   {
    "t": 93645.8333333333,
    "d": 1
   },
   {
    "t": 93750,
    "d": 4
   },
   {
    "t": 93750,
    "d": 2
   },
   {
    "t": 93958.3333333333,
    "d": 0
   },
   {
    "t": 93958.3333333333,
    "d": 1
   },
   {
    "t": 94166.6666666667,
    "d": 7
   },
   {
    "t": 94166.6666666667,
    "d": 3
   },
   {
    "t": 94375,
    "d": 5
   },
   {
    "t": 94375,
    "d": 2,
    "l": 546.875
   },
   {
    "t": 94583.3333333333,
    "d": 6
   },
   {
    "t": 94791.6666666667,
    "d": 4
   },
   {
    "t": 94999.6666666667,
    "d": 5,
    "l": 1172.20833333333
   },
   {
    "t": 95000,
    "d": 3,
    "l": 1354.16666666667
   },
   {
    "t": 96666.6666666667,
    "d": 0,
    "l": 234.375
   },
   {
    "t": 96979.1666666667,
    "d": 2,
    "l": 442.708333333333,
    "k": "noanim"
   }
  ]
 },
 "generatedBy": "Friday Night Funkin' - v0.8.4"
}